ws/__init__.py
ws/base.py
ws/client.py
ws/collector.py
ws/server.py
ws/exceptions/__init__.py
ws/exceptions/event.py
ws/exceptions/parameter.py
ws/models/__init__.py
ws/models/data.py
ws/models/message.py
ws/utils/__init__.py
ws/utils/converters.py
ws/utils/typing_checking.py
ws/wsprotocols/__init__.py
ws/wsprotocols/client.py
ws/wsprotocols/server.py
c_websockets-2.1.5.dist-info/LICENSE
c_websockets-2.1.5.dist-info/METADATA
c_websockets-2.1.5.dist-info/WHEEL
c_websockets-2.1.5.dist-info/top_level.txt
c_websockets-2.1.5.dist-info/RECORD
