Metadata-Version: 2.1
Name: c-websockets
Version: 2.1.5
Summary: WebSocket implementation in Python built on top of websockets python library. Similar to Node.js's ws.
Home-page: https://github.com/AceExpert/ws
Author: Cybertron
License: MIT
Project-URL: Issue Tracker, https://github.com/AceExpert/ws/issues
Project-URL: Contribute, https://github.com/AceExpert/ws/pulls
Classifier: Development Status :: 5 - Production/Stable
Classifier: License :: OSI Approved :: MIT License
Classifier: Intended Audience :: Developers
Classifier: Natural Language :: English
Classifier: Operating System :: OS Independent
Classifier: Programming Language :: Python :: 3
Classifier: Programming Language :: Python :: 3.8
Classifier: Programming Language :: Python :: 3.9
Classifier: Programming Language :: Python :: 3.12
Classifier: Topic :: Internet
Classifier: Topic :: Internet :: WWW/HTTP :: Session
Classifier: Topic :: Software Development :: Libraries
Classifier: Topic :: Software Development :: Libraries :: Python Modules
Classifier: Topic :: Utilities
Classifier: Typing :: Typed
Requires-Python: >=3.8.0
License-File: LICENSE
Requires-Dist: websockets
